sqlalchemy_solr/__init__.py
sqlalchemy_solr/api_globals.py
sqlalchemy_solr/base.py
sqlalchemy_solr/defaults.py
sqlalchemy_solr/http.py
sqlalchemy_solr/message_formatter.py
sqlalchemy_solr/release_flags.py
sqlalchemy_solr/solr_type_compiler.py
sqlalchemy_solr/type_map.py
sqlalchemy_solr/admin/solr_spec.py
sqlalchemy_solr/solrdbapi/__init__.py
sqlalchemy_solr/solrdbapi/_solrdbapi.py
sqlalchemy_solr/solrdbapi/api_exceptions.py
sqlalchemy_solr/solrdbapi/array.py
sqlalchemy_solr/solrdbapi/solr_reflect.py
sqlalchemy_solr-0.2.4.3.dist-info/AUTHORS
sqlalchemy_solr-0.2.4.3.dist-info/LICENSE
sqlalchemy_solr-0.2.4.3.dist-info/METADATA
sqlalchemy_solr-0.2.4.3.dist-info/WHEEL
sqlalchemy_solr-0.2.4.3.dist-info/entry_points.txt
sqlalchemy_solr-0.2.4.3.dist-info/top_level.txt
sqlalchemy_solr-0.2.4.3.dist-info/RECORD
