Metadata-Version: 2.1
Name: sqlalchemy_solr
Version: 0.2.4.3
Summary: Apache Solr Dialect for SQLAlchemy
Author: Ahmed Adel
Author-email: Ahmed Adel <hello@aadel.io>
License: MIT License
Project-URL: Homepage, https://github.com/aadel/sqlalchemy-solr
Project-URL: Issues, https://github.com/aadel/sqlalchemy-solr/issues
Keywords: Apache Solr,Solr,SQLAlchemy,dialect,Apache Superset
Classifier: Development Status :: 4 - Beta
Classifier: Environment :: Console
Classifier: Intended Audience :: Developers
Classifier: License :: OSI Approved :: MIT License
Classifier: Programming Language :: Python
Classifier: Programming Language :: Python :: 3
Classifier: Programming Language :: Python :: Implementation :: CPython
Classifier: Topic :: Database :: Front-Ends
Requires-Python: >=3.8
License-File: LICENSE
License-File: AUTHORS
Requires-Dist: sqlalchemy ~=1.4.7
Requires-Dist: python-dateutil ~=2.8.1
Requires-Dist: requests ~=2.31.0
Requires-Dist: sqlparse ~=0.4.4
